red_connector_ssh/__init__.py
red_connector_ssh/__main__.py
red_connector_ssh/cli_modes.py
red_connector_ssh/convert_ssh_key/__init__.py
red_connector_ssh/convert_ssh_key/__main__.py
red_connector_ssh/convert_ssh_key/main.py
red_connector_ssh/helpers.py
red_connector_ssh/main.py
red_connector_ssh/mount_dir.py
red_connector_ssh/schemas.py
red_connector_ssh/send_receive_dir.py
red_connector_ssh/send_receive_file.py
red_connector_ssh/version.py
red_connector_ssh-1.3.dist-info/entry_points.txt
red_connector_ssh-1.3.dist-info/LICENSE
red_connector_ssh-1.3.dist-info/WHEEL
red_connector_ssh-1.3.dist-info/METADATA
red_connector_ssh-1.3.dist-info/RECORD
