Metadata-Version: 2.1
Name: red-connector-ssh
Version: 1.3
Summary: RED Connector SSH is part of the Curious Containers project.
Home-page: https://www.curious-containers.cc/
License: AGPL-3.0
Author: Christoph Jansen
Author-email: Christoph.Jansen@htw-berlin.de
Requires-Python: >=3.6,<4.0
Classifier: License :: OSI Approved :: GNU Affero General Public License v3
Classifier: Programming Language :: Python :: 3
Classifier: Programming Language :: Python :: 3.10
Classifier: Programming Language :: Python :: 3.6
Classifier: Programming Language :: Python :: 3.7
Classifier: Programming Language :: Python :: 3.8
Classifier: Programming Language :: Python :: 3.9
Requires-Dist: jsonschema (>=3.0,<4.0)
Requires-Dist: paramiko (>=3.0,<4.0)
Requires-Dist: pexpect (>=4.7.0,<5.0.0)
Requires-Dist: scp (>=0.13.0,<0.14.0)
Project-URL: Repository, https://github.com/curious-containers/red-connector-ssh
